ship24/__init__.py
ship24/_hooks/__init__.py
ship24/_hooks/sdkhooks.py
ship24/_hooks/types.py
ship24/_version.py
ship24/api_for_per_call_plans.py
ship24/basesdk.py
ship24/couriers.py
ship24/errors/__init__.py
ship24/errors/apierror.py
ship24/errors/bulk_create_trackers_response_error.py
ship24/errors/error_response_format.py
ship24/errors/no_response_error.py
ship24/errors/responsevalidationerror.py
ship24/errors/ship24error.py
ship24/httpclient.py
ship24/models/__init__.py
ship24/models/bulk_create_trackers_request.py
ship24/models/bulk_create_trackers_response.py
ship24/models/bulk_create_trackersop.py
ship24/models/create_tracker_and_get_tracking_results_response.py
ship24/models/create_tracker_and_get_tracking_resultsop.py
ship24/models/create_trackerop.py
ship24/models/error_response_format.py
ship24/models/event.py
ship24/models/get_couriersop.py
ship24/models/get_tracker_by_trackeridop.py
ship24/models/get_tracking_results_of_tracker_by_trackeridop.py
ship24/models/get_tracking_results_of_trackers_by_tracking_numberop.py
ship24/models/get_trackingop.py
ship24/models/list_trackersop.py
ship24/models/resend_webhooksop.py
ship24/models/security.py
ship24/models/shipment.py
ship24/models/statistics.py
ship24/models/tracker.py
ship24/models/tracker_create_request.py
ship24/models/update_tracker_by_trackeridop.py
ship24/py.typed
ship24/sdk.py
ship24/sdkconfiguration.py
ship24/trackers.py
ship24/types/__init__.py
ship24/types/basemodel.py
ship24/utils/__init__.py
ship24/utils/annotations.py
ship24/utils/datetimes.py
ship24/utils/enums.py
ship24/utils/eventstreaming.py
ship24/utils/forms.py
ship24/utils/headers.py
ship24/utils/logger.py
ship24/utils/metadata.py
ship24/utils/queryparams.py
ship24/utils/requestbodies.py
ship24/utils/retries.py
ship24/utils/security.py
ship24/utils/serializers.py
ship24/utils/url.py
ship24/utils/values.py
ship24-0.2.0.dist-info/METADATA
ship24-0.2.0.dist-info/WHEEL
ship24-0.2.0.dist-info/RECORD
